fathompype/__init__.py
fathompype/azure_utils.py
fathompype/cleaning.py
fathompype/ingestion.py
fathompype/pipeline.py
fathompype-0.0.67.dist-info/METADATA
fathompype-0.0.67.dist-info/WHEEL
fathompype-0.0.67.dist-info/RECORD
