Metadata-Version: 2.1
Name: fathompype
Version: 0.0.67
Summary: 
Author: Sam Britton
Requires-Python: >=3.10,<4.0
Classifier: Programming Language :: Python :: 3
Classifier: Programming Language :: Python :: 3.10
Classifier: Programming Language :: Python :: 3.11
Classifier: Programming Language :: Python :: 3.12
Requires-Dist: azure-storage-blob (>=12.19.1,<13.0.0)
Requires-Dist: pandas (>=2.2.1,<3.0.0)
Requires-Dist: pyarrow (>=15.0.2,<16.0.0)
